uncertainpy/__init__.py
uncertainpy/_version.py
uncertainpy/data.py
uncertainpy/distribution.py
uncertainpy/parameters.py
uncertainpy/uncertainty.py
uncertainpy/version.py
uncertainpy/core/__init__.py
uncertainpy/core/base.py
uncertainpy/core/parallel.py
uncertainpy/core/run_model.py
uncertainpy/core/uncertainty_calculations.py
uncertainpy/features/__init__.py
uncertainpy/features/efel_features.py
uncertainpy/features/features.py
uncertainpy/features/general_network_features.py
uncertainpy/features/general_spiking_features.py
uncertainpy/features/network_features.py
uncertainpy/features/spikes.py
uncertainpy/features/spiking_features.py
uncertainpy/models/__init__.py
uncertainpy/models/model.py
uncertainpy/models/nest_model.py
uncertainpy/models/neuron_model.py
uncertainpy/plotting/__init__.py
uncertainpy/plotting/plot_uncertainty.py
uncertainpy/plotting/prettyplot/__init__.py
uncertainpy/plotting/prettyplot/prettyplot.py
uncertainpy/plotting/prettyplot/setup.py
uncertainpy/plotting/prettyplot/test_prettyplot.py
uncertainpy/utils/__init__.py
uncertainpy/utils/latex.py
uncertainpy/utils/logger.py
uncertainpy-0.9.0.dist-info/DESCRIPTION.rst
uncertainpy-0.9.0.dist-info/METADATA
uncertainpy-0.9.0.dist-info/RECORD
uncertainpy-0.9.0.dist-info/WHEEL
uncertainpy-0.9.0.dist-info/metadata.json
uncertainpy-0.9.0.dist-info/top_level.txt
