Metadata-Version: 2.0
Name: uncertainpy
Version: 0.9.0
Summary: Uncertainty quantification and sensitivity analysis of computational models and features of the models.
Home-page: https://github.com/simetenn/uncertainpy
Author: Simen Tennøe
Author-email: UNKNOWN
License: GNU GPLv3
Keywords: uncertainty quantification sensitivity analysis neuroscience
Platform: UNKNOWN
Requires-Python: >=2.7,<3
Requires-Dist: chaospy
Requires-Dist: h5py
Requires-Dist: matplotlib
Requires-Dist: multiprocess
Requires-Dist: numpy
Requires-Dist: scipy
Requires-Dist: seaborn
Requires-Dist: tqdm
Requires-Dist: xvfbwrapper
Provides-Extra: all
Requires-Dist: chaospy; extra == 'all'
Requires-Dist: efel; extra == 'all'
Requires-Dist: elephant; extra == 'all'
Requires-Dist: h5py; extra == 'all'
Requires-Dist: matplotlib; extra == 'all'
Requires-Dist: multiprocess; extra == 'all'
Requires-Dist: neo; extra == 'all'
Requires-Dist: numpy; extra == 'all'
Requires-Dist: quantities; extra == 'all'
Requires-Dist: scipy; extra == 'all'
Requires-Dist: seaborn; extra == 'all'
Requires-Dist: tqdm; extra == 'all'
Requires-Dist: xvfbwrapper; extra == 'all'
Provides-Extra: efel_features
Requires-Dist: efel; extra == 'efel_features'
Provides-Extra: network_features
Requires-Dist: elephant; extra == 'network_features'
Requires-Dist: neo; extra == 'network_features'
Requires-Dist: quantities; extra == 'network_features'
Provides-Extra: tests
Requires-Dist: chaospy; extra == 'tests'
Requires-Dist: click; extra == 'tests'
Requires-Dist: efel; extra == 'tests'
Requires-Dist: elephant; extra == 'tests'
Requires-Dist: h5py; extra == 'tests'
Requires-Dist: matplotlib; extra == 'tests'
Requires-Dist: multiprocess; extra == 'tests'
Requires-Dist: neo; extra == 'tests'
Requires-Dist: numpy; extra == 'tests'
Requires-Dist: quantities; extra == 'tests'
Requires-Dist: scipy; extra == 'tests'
Requires-Dist: seaborn; extra == 'tests'
Requires-Dist: tqdm; extra == 'tests'
Requires-Dist: xvfbwrapper; extra == 'tests'
